setup.py
birdback/__init__.py
birdback/xauth.py
birdback.egg-info/PKG-INFO
birdback.egg-info/SOURCES.txt
birdback.egg-info/dependency_links.txt
birdback.egg-info/not-zip-safe
birdback.egg-info/requires.txt
birdback.egg-info/top_level.txt