Metadata-Version: 1.1
Name: birdback
Version: 0.1b5
Summary: Birdback API client.
Home-page: https://github.com/Birdback/python-birdback.git
Author: Jean-Philippe Serafin
Author-email: dev@birdback.com
License: mit
Platform: any
Classifier: Development Status :: 4 - Beta
Classifier: Environment :: Web Environment
Classifier: Intended Audience :: Developers
Classifier: License :: OSI Approved :: MIT License
Classifier: Operating System :: OS Independent
Classifier: Programming Language :: Python
Classifier: Topic :: Internet :: WWW/HTTP :: Dynamic Content
Classifier: Topic :: Software Development :: Libraries :: Python Modules
